get_env_pass/__init__.py
get_env_pass-1.0.1.dist-info/LICENSE
get_env_pass-1.0.1.dist-info/METADATA
get_env_pass-1.0.1.dist-info/WHEEL
get_env_pass-1.0.1.dist-info/top_level.txt
get_env_pass-1.0.1.dist-info/RECORD
