Metadata-Version: 2.1
Name: get-env-pass
Version: 1.0.1
Summary: get-env-pass python package
Home-page: https://github.com/ccavales3/python-getenvpass
Author: Caesar Cavales
Author-email: c.cavales3@gmail.com
License: MIT
Platform: UNKNOWN
